{
  "type": "Struct",
  "name": "PortID",
  "description": "The unique ID of a port",
  "macros": [
    "#[derive(Debug, Clone, Copy, PartialEq, Eq, Hash, Serialize, Deserialize)]"
  ],
  "generics": [],
  "nonStandardTypes": [
    {
      "name": "ManifestID",
      "originalName": "ID",
      "fileAddress": "Library/code/manifest/types/id/ID"
    }
  ],
  "constants": [],
  "typeSpecificData": {
    "type": "Struct",
    "content": [
      {
        "macros": [],
        "name": "id",
        "type": "ManifestID",
        "description": null
      }
    ]
  },
  "exampleTexts": []
}